meeple/__init__.py
meeple/root.py
meeple/command/__init__.py
meeple/command/add.py
meeple/command/campaigns.py
meeple/command/collections.py
meeple/command/completions.py
meeple/command/delete.py
meeple/command/drop.py
meeple/command/find.py
meeple/command/hot.py
meeple/command/import_.py
meeple/command/info.py
meeple/command/list_.py
meeple/command/move.py
meeple/command/new.py
meeple/command/open_.py
meeple/command/rename.py
meeple/command/search.py
meeple/command/stats.py
meeple/command/update.py
meeple/type/__init__.py
meeple/type/bgg_collection_item.py
meeple/type/bgg_user.py
meeple/type/collection.py
meeple/type/collection_data.py
meeple/type/collection_state.py
meeple/type/item.py
meeple/type/item_credits.py
meeple/util/__init__.py
meeple/util/api_util.py
meeple/util/cmd_util.py
meeple/util/collection_util.py
meeple/util/completion_util.py
meeple/util/filter_util.py
meeple/util/fmt_util.py
meeple/util/fs_util.py
meeple/util/input_util.py
meeple/util/message_util.py
meeple/util/output_util.py
meeple/util/sort_util.py
meeple_cli-1.3.1.dist-info/entry_points.txt
meeple_cli-1.3.1.dist-info/LICENSE
meeple_cli-1.3.1.dist-info/WHEEL
meeple_cli-1.3.1.dist-info/METADATA
meeple_cli-1.3.1.dist-info/RECORD
