Metadata-Version: 2.1
Name: meeple-cli
Version: 1.3.1
Summary: Local board game collection manager. Powered by BoardGameGeek.
Author-email: Bradley Wojcik <bradleycwojcik@gmail.com>
Requires-Python: >=3.10
Classifier: License :: OSI Approved :: MIT License
Requires-Dist: arrow >=1
Requires-Dist: click >=8
Requires-Dist: rich >=13
Requires-Dist: xmltodict >=0.12.0
Requires-Dist: requests >=2
Requires-Dist: pyyaml >=6.0.1
Requires-Dist: black ; extra == "dev"
Requires-Dist: flake8 ; extra == "dev"
Requires-Dist: flit ; extra == "dev"
Requires-Dist: isort ; extra == "dev"
Requires-Dist: pre-commit ; extra == "dev"
Requires-Dist: homebrew-pypi-poet ; extra == "dev"
Requires-Dist: semgrep ; extra == "dev"
Requires-Dist: refurb ; extra == "dev"
Requires-Dist: pytest >=6 ; extra == "test"
Requires-Dist: pytest-cov ; extra == "test"
Requires-Dist: pytest-mock ; extra == "test"
Project-URL: Home, https://github.com/boldandbrad/meeple-cli
Provides-Extra: dev
Provides-Extra: test
